LICENSE
MANIFEST.in
README.md
requirements.txt
setup.cfg
setup.py
yolov6/__init__.py
yolov6/helpers.py
yolov6/assigners/__init__.py
yolov6/assigners/anchor_generator.py
yolov6/assigners/assigner_utils.py
yolov6/assigners/atss_assigner.py
yolov6/assigners/iou2d_calculator.py
yolov6/assigners/tal_assigner.py
yolov6/configs/__init__.py
yolov6/configs/yolov6l.py
yolov6/configs/yolov6l6.py
yolov6/configs/yolov6l6_finetune.py
yolov6/configs/yolov6l_finetune.py
yolov6/configs/yolov6m.py
yolov6/configs/yolov6m6.py
yolov6/configs/yolov6m6_finetune.py
yolov6/configs/yolov6m_finetune.py
yolov6/configs/yolov6n.py
yolov6/configs/yolov6n6.py
yolov6/configs/yolov6n6_finetune.py
yolov6/configs/yolov6n_finetune.py
yolov6/configs/yolov6s.py
yolov6/configs/yolov6s6.py
yolov6/configs/yolov6s6_finetune.py
yolov6/configs/yolov6s_finetune.py
yolov6/configs/base/__init__.py
yolov6/configs/base/yolov6l_base.py
yolov6/configs/base/yolov6l_base_finetune.py
yolov6/configs/base/yolov6m_base.py
yolov6/configs/base/yolov6m_base_finetune.py
yolov6/configs/base/yolov6n_base.py
yolov6/configs/base/yolov6n_base_finetune.py
yolov6/configs/base/yolov6s_base.py
yolov6/configs/base/yolov6s_base_finetune.py
yolov6/configs/experiment/__init__.py
yolov6/configs/experiment/eval_640_repro.py
yolov6/configs/experiment/yolov6n_with_eval_params.py
yolov6/configs/experiment/yolov6s_csp_scaled.py
yolov6/configs/experiment/yolov6t.py
yolov6/configs/experiment/yolov6t_csp_scaled.py
yolov6/configs/experiment/yolov6t_finetune.py
yolov6/configs/repopt/__init__.py
yolov6/configs/repopt/yolov6_tiny_hs.py
yolov6/configs/repopt/yolov6_tiny_opt.py
yolov6/configs/repopt/yolov6_tiny_opt_qat.py
yolov6/configs/repopt/yolov6n_hs.py
yolov6/configs/repopt/yolov6n_opt.py
yolov6/configs/repopt/yolov6n_opt_qat.py
yolov6/configs/repopt/yolov6s_hs.py
yolov6/configs/repopt/yolov6s_opt.py
yolov6/configs/repopt/yolov6s_opt_qat.py
yolov6/core/__init__.py
yolov6/core/engine.py
yolov6/core/evaler.py
yolov6/core/inferer.py
yolov6detect.egg-info/PKG-INFO
yolov6detect.egg-info/SOURCES.txt
yolov6detect.egg-info/dependency_links.txt
yolov6detect.egg-info/requires.txt
yolov6detect.egg-info/top_level.txt